quranallsbuforuni/__init__.py
quranallsbuforuni/module1.py
quranallsbuforuni/module2.py
quranallsbuforuni-0.0.2.dist-info/METADATA
quranallsbuforuni-0.0.2.dist-info/WHEEL
quranallsbuforuni-0.0.2.dist-info/top_level.txt
quranallsbuforuni-0.0.2.dist-info/RECORD
