Metadata-Version: 2.1
Name: quranallsbuforuni
Version: 0.0.2
Summary: Quran SBU All
Home-page: UNKNOWN
Author: Masoud Shafiei
Author-email: masoudshafiei89@yahoo.com
License: UNKNOWN
Keywords: quran,sbu
Platform: UNKNOWN
Classifier: Programming Language :: Python :: 3
